{
  "core_entities": [
    {
      "jargon": "Gut microbiota",
      "layman": "Gut bacteria"
    },
    {
      "jargon": "Mammalian species",
      "layman": "Types of mammals"
    },
    {
      "jargon": "Herbivores",
      "layman": "Plant-eaters"
    },
    {
      "jargon": "Omnivores",
      "layman": "Both plant and meat eaters"
    },
    {
      "jargon": "Carnivores",
      "layman": "Meat-eaters"
    }
  ],
  "methodologies": [
    {
      "jargon": "16S ribosomal RNA analysis",
      "layman": "DNA test for bacteria"
    },
    {
      "jargon": "Network-based analyses",
      "layman": "Pattern-based data analysis"
    },
    {
      "jargon": "Tree-based analyses",
      "layman": "Family tree analysis"
    },
    {
      "jargon": "Faecal bacterial census",
      "layman": "Counting gut bacteria in poop"
    },
    {
      "jargon": "Inter-generational transfer",
      "layman": "Passing gut bacteria from parent to child"
    }
  ],
  "outcomes": [
    {
      "jargon": "Microbial community diversity",
      "layman": "Variety of gut bacteria"
    },
    {
      "jargon": "Co-diversification",
      "layman": "Bacteria and hosts evolve together"
    },
    {
      "jargon": "Similar microbial communities",
      "layman": "Same bacteria in different animals"
    },
    {
      "jargon": "Diet as determinant",
      "layman": "Diet shapes gut bacteria"
    },
    {
      "jargon": "Microbial solution to herbivory",
      "layman": "Bacteria help plants-eaters digest food"
    }
  ]
}